setup.cfg
setup.py
az_distributions/Binomialdistribution.py
az_distributions/Gaussiandistribution.py
az_distributions/Generaldistribution.py
az_distributions/__init__.py
az_distributions.egg-info/PKG-INFO
az_distributions.egg-info/SOURCES.txt
az_distributions.egg-info/dependency_links.txt
az_distributions.egg-info/not-zip-safe
az_distributions.egg-info/top_level.txt